gnucashApi/__init__.py
gnucashApi/gnucash_api.py
gnucashApi/gnucash_report.py
gnucashApi/tree_search.py
gnucashApi/templates/__init__.py
gnucashApi/templates/report.template
gnucashapi-0.0.2.dist-info/METADATA
gnucashapi-0.0.2.dist-info/WHEEL
gnucashapi-0.0.2.dist-info/licenses/LICENSE
gnucashapi-0.0.2.dist-info/RECORD
