Metadata-Version: 2.1
Name: gnucashApi
Version: 0.0.2
Summary: This package provides a database API for gnucash SQL lite databases.
Author-email: SebGad <author@example.com>
License-File: LICENSE
Classifier: License :: OSI Approved :: MIT License
Classifier: Operating System :: OS Independent
Classifier: Programming Language :: Python :: 3
Requires-Python: >=3.7
